{
  "visualSlideImage": [
    {
      "pid": "01",
      "title": "Dex's CHOICE",
      "description": "Magnify Your Galaxy.",
      "src": "https://cdn-stamplib.casetify.com/cms/video/4a7a7c1cd669bf005e2cdc596b0345fa.mp4",
      "textBgColor": "yellow",
      "titleColor": "blue"
    },
    {
      "pid": "02",
      "title": "DISEL + CASTIBUY",
      "description": "Keep your tech edgy, stylish + protected.",
      "src": "https://cdn-stamplib.casetify.com/cms/video/8fe8b493e4cee12c8506d6d11f8481fc.mp4",
      "textBgColor": "blue",
      "titleColor": "yellow",
      "textColor": "white"
    },
    {
      "pid": "03",
      "title": "Upgrade Your Samsung S25 with a Kick-Stand",
      "description": "Unlock more protection and more productivity",
      "src": "https://cdn-stamplib.casetify.com/cms/image/5b730b163767a29c90e65e519a6de9cd.jpg",
      "textBgColor": "green",
      "titleColor": "yellow"
    },
    {
      "pid": "04",
      "title": "Your Phone, Your Style",
      "description": "Customize your iPhone 16",
      "src": "https://cdn-stamplib.casetify.com/cms/image/c639899a9049ddefbaa2ffb8462b09f5.jpg",
      "textBgColor": "pink",
      "titleColor": "blue"
    },
    {
      "pid": "05",
      "title": "Butterbear | CASTIBUY",
      "description": "Step into a paradise of spring desserts!",
      "src": "https://cdn-stamplib.casetify.com/cms/image/6f22430fa455e2df961f6d38a83c87d7.jpg",
      "textBgColor": "orange",
      "titleColor": "yellow"
    },
    {
      "pid": "06",
      "title": "Magsafe Accessories",
      "description": "Elevate Your Samsung S25 with Snappy Products",
      "src": "https://cdn-stamplib.casetify.com/cms/image/0738017a78a70038e2b7dfb5deba231c.jpg",
      "textBgColor": "yellow",
      "titleColor": "blue"
    }
  ],
  "featuredCollection": [
    {
      "pid": "01",
      "labelStyle": "pt-6 px-20 pb-4 text-white",
      "title": "바운스 캐리어",
      "image": "https://cdn-stamplib.casetify.com/cms/image/ad63df5cadcd88e2bc964d07dbf94060.jpg.webp",
      "buttonText": "구매하기",
      "layout": "even",
      "bgColor": "yellow"
    },
    {
      "pid": "02",
      "labelStyle": "pt-6 px-20 pb-4 text-white",
      "title": "[NEW] 갤럭시 S25 클리어 케이스",
      "image": "https://cdn-stamplib.casetify.com/cms/image/3ceeff23d688e17e6e0615233c8e0a2a.jpg.webp",
      "buttonText": "구매하기",
      "layout": "even",
      "bgColor": "blue"
    },
    {
      "pid": "03",
      "labelStyle": "pt-6 px-20 pb-4 text-white",
      "title": "BioVeg 시리즈",
      "image": "https://cdn-stamplib.casetify.com/cms/image/dccbe375af1dbb515e7052c291588d65.jpg.webp",
      "buttonText": "구매하기",
      "layout": "odd",
      "bgColor": "pink"
    },
    {
      "pid": "04",
      "labelStyle": "pt-6 px-20 pb-4 text-white",
      "title": "덱스's CHOiCE",
      "image": "https://cdn-stamplib.casetify.com/cms/image/f5a43413db50ef3ca10b73c841e73ac8.png.webp",
      "buttonText": "구매하기",
      "layout": "odd",
      "bgColor": "green"
    }
  ],
  "collaborator": [
    {
      "pid": "01",
      "title": "Diesel",
      "image": "https://cdn-stamplib.casetify.com/cms/image/47d76cd3743063321a4341816c26ef01.png.webp"
    },
    {
      "pid": "02",
      "title": "Cinderella",
      "image": "https://cdn-stamplib.casetify.com/cms/image/b390251c3d3d307e54e458bf22cb40d2.png.webp"
    },
    {
      "pid": "03",
      "title": "Tom and Jerry",
      "image": "https://cdn-stamplib.casetify.com/cms/image/d5df6fa8674c8f2369b02e3d4ac0dd75.png.webp"
    },
    {
      "pid": "04",
      "title": "Maison Kitsuné",
      "image": "https://cdn-stamplib.casetify.com/cms/image/4c2b7b430f06df259a30671774b7df57.png.webp"
    },
    {
      "pid": "05",
      "title": "Chill Guy",
      "image": "https://cdn-stamplib.casetify.com/cms/image/5bb5e72d797d604a9a017b56dc99f2d8.png.webp"
    },
    {
      "pid": "06",
      "title": "Chiikawa",
      "image": "https://cdn-stamplib.casetify.com/cms/image/7cc45cd006a560191ba3770dea2c6e4c.png.webp"
    },
    {
      "pid": "07",
      "title": "Hello Kitty",
      "image": "https://cdn-stamplib.casetify.com/cms/image/8ded8f26d9234c934d3c828c655fcf73.png.webp"
    },
    {
      "pid": "08",
      "title": "Kuromi",
      "image": "https://cdn-stamplib.casetify.com/cms/image/798123f8fc50e5ccd5d1a886b3bc8a40.png.webp"
    }
  ],
  "essentials": [
    {
      "pid": "01",
      "title": "Rope Cross-body Strap - Black (Double End)",
      "image": "https://cdn-stamplib.casetify.com/cms/image/27c4526973c3c27b6759bba3489ba54a.png.webp",
      "bgColor": "green"
    },
    {
      "pid": "02",
      "title": "Impact Anti-Blue Light Screen Protector",
      "image": "https://cdn-stamplib.casetify.com/cms/image/138d3c1505bc6508c8a182e508ae0a1a.png.webp",
      "bgColor": "pink"
    },
    {
      "pid": "03",
      "title": "The Bounce Odyssey Band™",
      "image": "https://cdn-stamplib.casetify.com/cms/image/7197f6deb7b9c33b993a6280a7054923.png.webp",
      "bgColor": "gray"
    },
    {
      "pid": "04",
      "title": "Camera Lens Protector",
      "image": "https://cdn-stamplib.casetify.com/cms/image/2529754d0752a65694bb263b5d490877.png.webp",
      "bgColor": "blue"
    },
    {
      "pid": "05",
      "title": "Camera Lens Gem",
      "image": "https://cdn-stamplib.casetify.com/cms/image/4aa1903971c47f4edce13a1fc2c6cffe.jpg.webp",
      "bgColor": "orange"
    },
    {
      "pid": "06",
      "title": "Snappy™ Cardholder Stand",
      "image": "https://cdn-image02.casetify.com/usr/4787/34787/~v419/30136034_snappy-cardholder-stand__color_black_16005956__render40.png.560x560-w.webp",
      "bgColor": "yellow"
    },
    {
      "pid": "07",
      "title": "Snappy™ Mirror Grip Stand",
      "image": "https://cdn-image02.casetify.com/usr/4787/34787/~v21/30133549_snappy-grip-stand__color_black_16006464__render40.png.560x560-w.webp",
      "bgColor": "green"
    }
  ],
  "trendingDesigns": [
    {
      "pid": "01",
      "title": "Kitten Ribbon",
      "image": "https://cdn-image02.casetify.com/usr/21890/26571890/~v114/32570971_iphone-16-pro-max__color_natural-titanium_16007168.png.560x560-w.webp",
      "bgColor": "yellow",
      "btnText": "구매하기",
      "btnStyle": "py-12 px-20 text-20 rounded-20"
    },
    {
      "pid": "02",
      "title": "Cross Heritage",
      "image": "https://cdn-image02.casetify.com/usr/4787/34787/~v111/32851163_samsung-galaxy-s25-ultra__color_natural-titanium_16008477.png.560x560-w.webp",
      "bgColor": "pink",
      "btnText": "구매하기",
      "btnStyle": "py-12 px-20 text-20 rounded-20"
    },
    {
      "pid": "03",
      "title": "Brace For Impact",
      "image": "https://cdn-image02.casetify.com/usr/27391/11607391/~v7711/11526672_samsung-galaxy-s25-ultra__color_silver_16008466.png.560x560-w.webp",
      "bgColor": "blue",
      "btnText": "구매하기",
      "btnStyle": "py-12 px-20 text-20 rounded-20"
    },
    {
      "pid": "04",
      "title": "Denim",
      "image": "https://cdn-image02.casetify.com/usr/4787/34787/~v111/32719682_samsung-galaxy-s25-ultra__color_natural-titanium_16008458.png.560x560-w.webp",
      "bgColor": "green",
      "btnText": "구매하기",
      "btnStyle": "py-12 px-20 text-20 rounded-20"
    },
    {
      "pid": "05",
      "title": "404 NOT FOUND",
      "image": "https://cdn-image02.casetify.com/usr/16571/16546571/~v1/33933541_keychain-tag_16008557.png.560x560-w.webp",
      "bgColor": "orange",
      "btnText": "구매하기",
      "btnStyle": "py-12 px-20 text-20 rounded-20"
    },
    {
      "pid": "06",
      "title": "Cross heritage",
      "image": "https://cdn-image02.casetify.com/usr/4787/34787/~v111/32910493_snappy-cardholder-stand__color_black_16006465__render40.png.560x560-w.webp",
      "bgColor": "gray",
      "btnText": "구매하기",
      "btnStyle": "py-12 px-20 text-20 rounded-20"
    }
  ],
  "artist": [
    {
      "no": "01",
      "labelStyle": "pt-6 px-20 pb-4 text-white",
      "title": "PETTYDUST",
      "image": "https://cdn-stamplib.casetify.com/cms/image/aef1e391974e98eb2385e527537d63e6.jpg.webp",
      "bgColor": "blue",
      "btnText": "지금 구매하기",
      "btnStyle": "py-12 px-20 text-20 rounded-20 text-white"
    },
    {
      "no": "02",
      "labelStyle": "pt-6 px-20 pb-4 text-white",
      "title": "Matsui",
      "image": "https://cdn-stamplib.casetify.com/cms/image/5c7a594e098945ef4eba12168a169031.png.webp",
      "bgColor": "green",
      "btnText": "지금 구매하기",
      "btnStyle": "py-12 px-20 text-20 rounded-20"
    },
    {
      "no": "03",
      "labelStyle": "pt-6 px-20 pb-4 text-white",
      "title": "Skater JOHN",
      "image": "https://cdn-stamplib.casetify.com/cms/image/10cdcf83013db7ed4d00f415ef90511d.png.webp",
      "bgColor": "orange",
      "btnText": "지금 구매하기",
      "btnStyle": "py-12 px-20 text-20 rounded-20"
    }
  ],
  "ourMission": [
    {
      "title": "Re/CASETiBUY",
      "description": "Re/CLAIM Re/IMAGINE Re/CASETiFY",
      "image": "https://cdn-stamplib.casetify.com/cms/image/43ef6f3e58588c393e0a900dcf9577bc.png.webp",
      "src": "https://cdn-stamplib.casetify.com/cms/image/489e4dfd03592490676e727c133d2a30.gif",
      "bgColor": "lightgreen",
      "btnText": "더 알아보기",
      "btnStyle": "py-12 px-20 text-20 rounded-20"
    }
  ],
  "Community": [
    {
      "label": "인플루언서",
      "labelStyle": "pt-6 px-20 pb-4 text-white",
      "title": "@suj_q X Black Organza Ribbon",
      "image": "https://cdn-stamplib.casetify.com/cms/image/1d7016de80d4837b84b3a896355c457b.jpg.webp",
      "bgColor": "yellow",
      "btnText": "구매하기",
      "btnStyle": "py-12 px-20 text-20 rounded-20"
    },
    {
      "label": "모델",
      "labelStyle": "pt-6 px-20 pb-4 text-white",
      "title": "@chae_byungeun X Label Sticker Design 2",
      "image": "https://cdn-stamplib.casetify.com/cms/image/5244f84a309901a10d52dbae3016f8c5.jpg.webp",
      "bgColor": "pink",
      "btnText": "구매하기",
      "btnStyle": "py-12 px-20 text-20 rounded-20"
    },
    {
      "label": "컨텐츠 크리에이터",
      "labelStyle": "pt-6 px-20 pb-4 text-white",
      "title": "@yourbeloved_ria X transparent flowers",
      "image": "https://cdn-stamplib.casetify.com/cms/image/5244f84a309901a10d52dbae3016f8c5.jpg.webp",
      "bgColor": "blue",
      "btnText": "구매하기",
      "btnStyle": "py-12 px-20 text-20 rounded-20 text-white"
    }
  ],
  "news": [
    {
      "no": "1",
      "title": "Protective Phone Case for iPhone 16",
      "description": "Keep your iPhone 16 protected with the Ultra Bounce Case. Find out more tips on how to...",
      "image": "https://cdn-stamplib.casetify.com/cms/image/3dfd5b5a3af445a52f5feee5e7eaa4ec.jpg.webp",
      "bgColor": "green",
      "btnText": "더 알아보기",
      "btnStyle": "py-12 px-20 text-20 rounded-20"
    },
    {
      "no": "2",
      "title": "Minimalist iPhone Case Is Your New...",
      "description": "Discover why our silicone phone case from Essentials by CASETiFY™ isn’t just a phone cover...",
      "image": "https://cdn-stamplib.casetify.com/cms/image/667a1c3854a74908151c2d3e8341787e.jpg.webp",
      "bgColor": "yellow",
      "btnText": "더 알아보기",
      "btnStyle": "py-12 px-20 text-20 rounded-20"
    },
    {
      "no": "3",
      "title": "CASETiBUY’s PowerThru by CASETiBUY™...",
      "description": "CASETiBUY expands its product portfolio to include a wider range of powerful and convenient...",
      "image": "https://cdn-stamplib.casetify.com/cms/image/97d16ec561baee701d9cb0ec036a5d2e.jpg.webp",
      "bgColor": "pink",
      "btnText": "더 알아보기",
      "btnStyle": "py-12 px-20 text-20 rounded-20"
    },
    {
      "no": "4",
      "title": "What Is a Military-Grade Phone...",
      "description": "Learn about the rigorous MIL-STD testing and what the “military-grade phone cases” are....",
      "image": "https://cdn-stamplib.casetify.com/cms/image/88da9bd9188ff0fa48b9bb2ebcf78704.jpg.webp",
      "bgColor": "blue",
      "btnText": "더 알아보기",
      "btnStyle": "py-12 px-20 text-20 rounded-20 text-white"
    }
  ],
  "club": [
    {
      "title": "CASETiBUY Club",
      "description": "케이스티버이 클럽 회원 전용 혜택 받아보기",
      "src": "https://cdn-stamplib.casetify.com/cms/image/82530d836f5bd685f4169e4c9b6d1b2b.jpg.webp",
      "textBgColor": "yellow",
      "titleColor": "blue"
    }
  ]
}
